{
  "workflow_id": "pack-kyb-beneficial-ownership-attribution",
  "name": "KYB Beneficial Ownership Attribution",
  "outcome": "Gated two-step bank KYB chain under FinCEN CDD Rule 31 CFR 1010.230. Step 1 computes indirect natural-person beneficial ownership via recursive ownership-tier multiplication (25% threshold). Gate on /is_beneficial_owner: false exits early (no beneficial owner at or above 25%). Default (true, beneficial owner identified) proceeds to Step 2: W-8 series structural validation for withholding compliance. NOT the CTA/BOI domestic reporting rule. Synthetic entity IDs only. Zero PII by construction.",
  "spec_version": "ocg-control-plane@1",
  "manifest": {
    "manifest_version": "1",
    "workflow_id": "pack-kyb-beneficial-ownership-attribution",
    "trigger": {
      "type": "manual"
    },
    "nodes": [
      {
        "node_id": "n1",
        "kernel_id": "art-268-compute-cdd-ownership-25pct",
        "kernel_digest": "sha256:0dc3051e04237f9ec574f8ef5ff8b7c1eefcbd0e415204906089b327c6a90378"
      },
      {
        "node_id": "n2",
        "kernel_id": "art-269-validate-w8-series-structural",
        "kernel_digest": "sha256:a1851d45c46b04a84e8841137e3fe46ec0b91c345ba39ce7ce125fe9e446ce5e"
      }
    ],
    "connectors": [],
    "gates": [],
    "actions": []
  },
  "workflow_manifest_digest": "sha256:c25fc0e60062f224aef4497896c02c497d7392f910827bdc9eab9cf6d6864224",
  "declared_inputs": [],
  "steps_meta": [
    {
      "node_id": "n1",
      "data_classification": "compute"
    },
    {
      "node_id": "n2",
      "data_classification": "compute"
    }
  ]
}
