{
  "tool_id": "art-408-evidence-bundle-tier-labeler",
  "note": "golden_hash computed directly via executionHash at fixture-authoring time. 3 vectors per tier (Verify/Execute/Prove) plus 1 UNLABELED negative case.",
  "vectors": [
    {
      "name": "verify-only-artifact-a",
      "description": "Envelope well-formed and execution_hash recomputes; chain-execution not declared -- qualifies for OCG-Verify only.",
      "policy_parameters": {
        "artifact_tool_id": "art-04-agent-identity-attestation-checker",
        "artifact_execution_hash": "sha256:aaaa1111",
        "proof_refs": ["receipt:art-04-envelope-check"],
        "gate_results": {
          "envelope_well_formed": true,
          "execution_hash_recomputes": true,
          "chain_execution_valid": false,
          "mandate_gates_valid": false,
          "compute_integrity_proof_valid": false
        }
      },
      "output_payload": {
        "artifact_tool_id": "art-04-agent-identity-attestation-checker",
        "artifact_execution_hash": "sha256:aaaa1111",
        "tier_label": "OCG-Verify",
        "eligible_tiers": ["OCG-Verify"],
        "gate_provenance": {
          "envelope_well_formed": true,
          "execution_hash_recomputes": true,
          "chain_execution_valid": false,
          "mandate_gates_valid": false,
          "compute_integrity_proof_valid": false
        },
        "proof_refs": ["receipt:art-04-envelope-check"],
        "proof_ref_count": 1,
        "note": "The tiered label re-expresses existing §15 gate-pass results; it adds no new gate and mints no new trust claim (SPEC.md §SIDECAR.1).",
        "disambiguation": "This node does not re-run §1/§4/§18/§21/§22 gates itself -- gate_results is a caller declaration of prior gate outcomes for the referenced artifact, not independently re-verified here."
      },
      "compliance_flags": ["EVIDENCE_BUNDLE_ASSEMBLED", "SIDECAR_TIER_OCG_VERIFY"],
      "golden_hash": "9a22d4790a144dd30d1162b0a2dcb7787abe30b1bdd7edd0ae97cc07bac824a9"
    },
    {
      "name": "verify-only-artifact-b",
      "description": "Second OCG-Verify-only artifact -- envelope/hash gates hold, chain-execution not declared.",
      "policy_parameters": {
        "artifact_tool_id": "art-12-acp-checkout-conformance-validator",
        "artifact_execution_hash": "sha256:bbbb2222",
        "proof_refs": [],
        "gate_results": {
          "envelope_well_formed": true,
          "execution_hash_recomputes": true,
          "chain_execution_valid": false,
          "mandate_gates_valid": true,
          "compute_integrity_proof_valid": false
        }
      },
      "output_payload": {
        "artifact_tool_id": "art-12-acp-checkout-conformance-validator",
        "artifact_execution_hash": "sha256:bbbb2222",
        "tier_label": "OCG-Verify",
        "eligible_tiers": ["OCG-Verify"],
        "gate_provenance": {
          "envelope_well_formed": true,
          "execution_hash_recomputes": true,
          "chain_execution_valid": false,
          "mandate_gates_valid": true,
          "compute_integrity_proof_valid": false
        },
        "proof_refs": [],
        "proof_ref_count": 0,
        "note": "The tiered label re-expresses existing §15 gate-pass results; it adds no new gate and mints no new trust claim (SPEC.md §SIDECAR.1).",
        "disambiguation": "This node does not re-run §1/§4/§18/§21/§22 gates itself -- gate_results is a caller declaration of prior gate outcomes for the referenced artifact, not independently re-verified here."
      },
      "compliance_flags": ["EVIDENCE_BUNDLE_ASSEMBLED", "SIDECAR_TIER_OCG_VERIFY"],
      "golden_hash": "955af0e2820ab8e2ced422c0e657b06d83dc08942dee33c3f92da112699d6a60"
    },
    {
      "name": "verify-only-artifact-c",
      "description": "Third OCG-Verify-only artifact -- mandate gates declared false, so tier caps at Verify.",
      "policy_parameters": {
        "artifact_tool_id": "art-122-timestamp-attestation-verifier",
        "artifact_execution_hash": "sha256:cccc3333",
        "proof_refs": ["receipt:art-122-tsa"],
        "gate_results": {
          "envelope_well_formed": true,
          "execution_hash_recomputes": true,
          "chain_execution_valid": true,
          "mandate_gates_valid": false,
          "compute_integrity_proof_valid": false
        }
      },
      "output_payload": {
        "artifact_tool_id": "art-122-timestamp-attestation-verifier",
        "artifact_execution_hash": "sha256:cccc3333",
        "tier_label": "OCG-Verify",
        "eligible_tiers": ["OCG-Verify"],
        "gate_provenance": {
          "envelope_well_formed": true,
          "execution_hash_recomputes": true,
          "chain_execution_valid": true,
          "mandate_gates_valid": false,
          "compute_integrity_proof_valid": false
        },
        "proof_refs": ["receipt:art-122-tsa"],
        "proof_ref_count": 1,
        "note": "The tiered label re-expresses existing §15 gate-pass results; it adds no new gate and mints no new trust claim (SPEC.md §SIDECAR.1).",
        "disambiguation": "This node does not re-run §1/§4/§18/§21/§22 gates itself -- gate_results is a caller declaration of prior gate outcomes for the referenced artifact, not independently re-verified here."
      },
      "compliance_flags": ["EVIDENCE_BUNDLE_ASSEMBLED", "SIDECAR_TIER_OCG_VERIFY"],
      "golden_hash": "90de284978ec1f6af6ccc26307e817d752ff674a9362b17412b1fec7bf9e9964"
    },
    {
      "name": "execute-artifact-a",
      "description": "Envelope/hash + chain-execution + mandate gates all hold, no compute-integrity proof -- OCG-Execute.",
      "policy_parameters": {
        "artifact_tool_id": "art-147-mcp-server-identity-attestation-validator",
        "artifact_execution_hash": "sha256:dddd4444",
        "proof_refs": ["receipt:art-147-envelope", "receipt:art-147-mandate"],
        "gate_results": {
          "envelope_well_formed": true,
          "execution_hash_recomputes": true,
          "chain_execution_valid": true,
          "mandate_gates_valid": true,
          "compute_integrity_proof_valid": false
        }
      },
      "output_payload": {
        "artifact_tool_id": "art-147-mcp-server-identity-attestation-validator",
        "artifact_execution_hash": "sha256:dddd4444",
        "tier_label": "OCG-Execute",
        "eligible_tiers": ["OCG-Verify", "OCG-Execute"],
        "gate_provenance": {
          "envelope_well_formed": true,
          "execution_hash_recomputes": true,
          "chain_execution_valid": true,
          "mandate_gates_valid": true,
          "compute_integrity_proof_valid": false
        },
        "proof_refs": ["receipt:art-147-envelope", "receipt:art-147-mandate"],
        "proof_ref_count": 2,
        "note": "The tiered label re-expresses existing §15 gate-pass results; it adds no new gate and mints no new trust claim (SPEC.md §SIDECAR.1).",
        "disambiguation": "This node does not re-run §1/§4/§18/§21/§22 gates itself -- gate_results is a caller declaration of prior gate outcomes for the referenced artifact, not independently re-verified here."
      },
      "compliance_flags": ["EVIDENCE_BUNDLE_ASSEMBLED", "SIDECAR_TIER_OCG_EXECUTE"],
      "golden_hash": "e458da9d9d5a097cd8a4915e0b156d61bf2af0ffa6ff86d016a6675b6fd06367"
    },
    {
      "name": "execute-artifact-b",
      "description": "Second OCG-Execute artifact -- same gate shape, distinct artifact reference.",
      "policy_parameters": {
        "artifact_tool_id": "art-149-mcp-registry-entry-conformance",
        "artifact_execution_hash": "sha256:eeee5555",
        "proof_refs": ["receipt:art-149-envelope"],
        "gate_results": {
          "envelope_well_formed": true,
          "execution_hash_recomputes": true,
          "chain_execution_valid": true,
          "mandate_gates_valid": true,
          "compute_integrity_proof_valid": false
        }
      },
      "output_payload": {
        "artifact_tool_id": "art-149-mcp-registry-entry-conformance",
        "artifact_execution_hash": "sha256:eeee5555",
        "tier_label": "OCG-Execute",
        "eligible_tiers": ["OCG-Verify", "OCG-Execute"],
        "gate_provenance": {
          "envelope_well_formed": true,
          "execution_hash_recomputes": true,
          "chain_execution_valid": true,
          "mandate_gates_valid": true,
          "compute_integrity_proof_valid": false
        },
        "proof_refs": ["receipt:art-149-envelope"],
        "proof_ref_count": 1,
        "note": "The tiered label re-expresses existing §15 gate-pass results; it adds no new gate and mints no new trust claim (SPEC.md §SIDECAR.1).",
        "disambiguation": "This node does not re-run §1/§4/§18/§21/§22 gates itself -- gate_results is a caller declaration of prior gate outcomes for the referenced artifact, not independently re-verified here."
      },
      "compliance_flags": ["EVIDENCE_BUNDLE_ASSEMBLED", "SIDECAR_TIER_OCG_EXECUTE"],
      "golden_hash": "7cfe22059e5c38e053e3c4c137de5b8bdc0afedea2d1d4a6eaaf349aed1560cb"
    },
    {
      "name": "execute-artifact-c",
      "description": "Third OCG-Execute artifact -- compute-integrity gate explicitly declared false, caps at Execute.",
      "policy_parameters": {
        "artifact_tool_id": "art-159-vida-einvoice-en16931-conformance-validator",
        "artifact_execution_hash": "sha256:ffff6666",
        "proof_refs": ["receipt:art-159-envelope", "receipt:art-159-mandate"],
        "gate_results": {
          "envelope_well_formed": true,
          "execution_hash_recomputes": true,
          "chain_execution_valid": true,
          "mandate_gates_valid": true,
          "compute_integrity_proof_valid": false
        }
      },
      "output_payload": {
        "artifact_tool_id": "art-159-vida-einvoice-en16931-conformance-validator",
        "artifact_execution_hash": "sha256:ffff6666",
        "tier_label": "OCG-Execute",
        "eligible_tiers": ["OCG-Verify", "OCG-Execute"],
        "gate_provenance": {
          "envelope_well_formed": true,
          "execution_hash_recomputes": true,
          "chain_execution_valid": true,
          "mandate_gates_valid": true,
          "compute_integrity_proof_valid": false
        },
        "proof_refs": ["receipt:art-159-envelope", "receipt:art-159-mandate"],
        "proof_ref_count": 2,
        "note": "The tiered label re-expresses existing §15 gate-pass results; it adds no new gate and mints no new trust claim (SPEC.md §SIDECAR.1).",
        "disambiguation": "This node does not re-run §1/§4/§18/§21/§22 gates itself -- gate_results is a caller declaration of prior gate outcomes for the referenced artifact, not independently re-verified here."
      },
      "compliance_flags": ["EVIDENCE_BUNDLE_ASSEMBLED", "SIDECAR_TIER_OCG_EXECUTE"],
      "golden_hash": "5418a96edff7aa3db25b5d6d30ec33888da6dc7b65b0675bcc302318048ddc31"
    },
    {
      "name": "prove-artifact-a",
      "description": "All five gates hold including a verified §18 compute-integrity proof -- OCG-Prove, the top tier.",
      "policy_parameters": {
        "artifact_tool_id": "art-171-iso42001-aims-clause-conformance",
        "artifact_execution_hash": "sha256:11117777",
        "proof_refs": ["receipt:art-171-envelope", "receipt:art-171-mandate", "proof:art-171-risc0-groth16"],
        "gate_results": {
          "envelope_well_formed": true,
          "execution_hash_recomputes": true,
          "chain_execution_valid": true,
          "mandate_gates_valid": true,
          "compute_integrity_proof_valid": true
        }
      },
      "output_payload": {
        "artifact_tool_id": "art-171-iso42001-aims-clause-conformance",
        "artifact_execution_hash": "sha256:11117777",
        "tier_label": "OCG-Prove",
        "eligible_tiers": ["OCG-Verify", "OCG-Execute", "OCG-Prove"],
        "gate_provenance": {
          "envelope_well_formed": true,
          "execution_hash_recomputes": true,
          "chain_execution_valid": true,
          "mandate_gates_valid": true,
          "compute_integrity_proof_valid": true
        },
        "proof_refs": ["receipt:art-171-envelope", "receipt:art-171-mandate", "proof:art-171-risc0-groth16"],
        "proof_ref_count": 3,
        "note": "The tiered label re-expresses existing §15 gate-pass results; it adds no new gate and mints no new trust claim (SPEC.md §SIDECAR.1).",
        "disambiguation": "This node does not re-run §1/§4/§18/§21/§22 gates itself -- gate_results is a caller declaration of prior gate outcomes for the referenced artifact, not independently re-verified here."
      },
      "compliance_flags": ["EVIDENCE_BUNDLE_ASSEMBLED", "SIDECAR_TIER_OCG_PROVE"],
      "golden_hash": "6427e2af140d0f78aeeeadc68fbff510db6fbce03115cdc99cca13a4229d55e9"
    },
    {
      "name": "prove-artifact-b",
      "description": "Second OCG-Prove artifact -- distinct proof reference, same gate shape.",
      "policy_parameters": {
        "artifact_tool_id": "art-213-fx-settlement-netting-kernel",
        "artifact_execution_hash": "sha256:22228888",
        "proof_refs": ["proof:art-213-risc0-groth16"],
        "gate_results": {
          "envelope_well_formed": true,
          "execution_hash_recomputes": true,
          "chain_execution_valid": true,
          "mandate_gates_valid": true,
          "compute_integrity_proof_valid": true
        }
      },
      "output_payload": {
        "artifact_tool_id": "art-213-fx-settlement-netting-kernel",
        "artifact_execution_hash": "sha256:22228888",
        "tier_label": "OCG-Prove",
        "eligible_tiers": ["OCG-Verify", "OCG-Execute", "OCG-Prove"],
        "gate_provenance": {
          "envelope_well_formed": true,
          "execution_hash_recomputes": true,
          "chain_execution_valid": true,
          "mandate_gates_valid": true,
          "compute_integrity_proof_valid": true
        },
        "proof_refs": ["proof:art-213-risc0-groth16"],
        "proof_ref_count": 1,
        "note": "The tiered label re-expresses existing §15 gate-pass results; it adds no new gate and mints no new trust claim (SPEC.md §SIDECAR.1).",
        "disambiguation": "This node does not re-run §1/§4/§18/§21/§22 gates itself -- gate_results is a caller declaration of prior gate outcomes for the referenced artifact, not independently re-verified here."
      },
      "compliance_flags": ["EVIDENCE_BUNDLE_ASSEMBLED", "SIDECAR_TIER_OCG_PROVE"],
      "golden_hash": "7d31373b61970b2edbfdec19b3a310af88f4bb7a79f9c00773ff51d5a277ae64"
    },
    {
      "name": "prove-artifact-c",
      "description": "Third OCG-Prove artifact -- multiple stacked proof refs.",
      "policy_parameters": {
        "artifact_tool_id": "art-279-vr-1-state-proof-kernel",
        "artifact_execution_hash": "sha256:33339999",
        "proof_refs": ["receipt:art-279-envelope", "proof:art-279-risc0-groth16", "anchor:art-279-jades"],
        "gate_results": {
          "envelope_well_formed": true,
          "execution_hash_recomputes": true,
          "chain_execution_valid": true,
          "mandate_gates_valid": true,
          "compute_integrity_proof_valid": true
        }
      },
      "output_payload": {
        "artifact_tool_id": "art-279-vr-1-state-proof-kernel",
        "artifact_execution_hash": "sha256:33339999",
        "tier_label": "OCG-Prove",
        "eligible_tiers": ["OCG-Verify", "OCG-Execute", "OCG-Prove"],
        "gate_provenance": {
          "envelope_well_formed": true,
          "execution_hash_recomputes": true,
          "chain_execution_valid": true,
          "mandate_gates_valid": true,
          "compute_integrity_proof_valid": true
        },
        "proof_refs": ["receipt:art-279-envelope", "proof:art-279-risc0-groth16", "anchor:art-279-jades"],
        "proof_ref_count": 3,
        "note": "The tiered label re-expresses existing §15 gate-pass results; it adds no new gate and mints no new trust claim (SPEC.md §SIDECAR.1).",
        "disambiguation": "This node does not re-run §1/§4/§18/§21/§22 gates itself -- gate_results is a caller declaration of prior gate outcomes for the referenced artifact, not independently re-verified here."
      },
      "compliance_flags": ["EVIDENCE_BUNDLE_ASSEMBLED", "SIDECAR_TIER_OCG_PROVE"],
      "golden_hash": "709668d120bf42d6621babc6825588c47a7941fa12947bd9e7b1260a41dedec3"
    },
    {
      "name": "unlabeled-envelope-invalid",
      "description": "Envelope declared not well-formed -- no tier qualifies, UNLABELED with the failure flag.",
      "policy_parameters": {
        "artifact_tool_id": "art-999-hypothetical-malformed-artifact",
        "artifact_execution_hash": "",
        "proof_refs": [],
        "gate_results": {
          "envelope_well_formed": false,
          "execution_hash_recomputes": false,
          "chain_execution_valid": false,
          "mandate_gates_valid": false,
          "compute_integrity_proof_valid": false
        }
      },
      "output_payload": {
        "artifact_tool_id": "art-999-hypothetical-malformed-artifact",
        "artifact_execution_hash": "",
        "tier_label": "UNLABELED",
        "eligible_tiers": [],
        "gate_provenance": {
          "envelope_well_formed": false,
          "execution_hash_recomputes": false,
          "chain_execution_valid": false,
          "mandate_gates_valid": false,
          "compute_integrity_proof_valid": false
        },
        "proof_refs": [],
        "proof_ref_count": 0,
        "note": "The tiered label re-expresses existing §15 gate-pass results; it adds no new gate and mints no new trust claim (SPEC.md §SIDECAR.1).",
        "disambiguation": "This node does not re-run §1/§4/§18/§21/§22 gates itself -- gate_results is a caller declaration of prior gate outcomes for the referenced artifact, not independently re-verified here."
      },
      "compliance_flags": ["EVIDENCE_BUNDLE_ASSEMBLED", "SIDECAR_UNLABELED_GATES_FAILED", "SIDECAR_NO_ARTIFACT_HASH_DECLARED"],
      "golden_hash": "fe3da628232c2fd088d209094580a48b39731696bb680b687e846768d52bed8c"
    }
  ]
}
