{
  "tool_id": "art-81-allocation-affirmation-conformance",
  "note": "golden_hash empty until first `node golden-parity.test.mjs --update`.",
  "vectors": [
    {
      "name": "default-inputs",
      "policy_parameters": {},
      "output_payload": {
        "on_time_rate": 100,
        "total_events": 0,
        "on_time_events": 0,
        "events_flagged": [],
        "format_nonconformance_count": 0,
        "cutoff_applied": "23:00",
        "cutoff_timezone": "CET (Central European Time)",
        "reference": {
          "rts": "ESMA CSDR SDR RTS — Final Report 13 Oct 2025 (ESMA74-2119945926-3430)",
          "rule": "Same-day allocation/confirmation by 23:00 CET + machine-readable formats from December 2026",
          "note": "Verify current applicability date. \"Dec 2026\" refers to the ESMA RTS binding date — confirm final text."
        },
        "dual_date_note": "Allocation/confirmation timing rules binding DEC 2026 · T+1 go-live 11 OCT 2027 — verify current (CSDR Refit/RTS still finalising)",
        "note": "DECISION-SUPPORT DRAFT — not a regulatory finding. Timestamps are compared in the timezone provided (assumed CET). Verify all event timestamps are in CET/CEST as applicable. Machine-readable format requirement: verify final format specification against ESMA RTS."
      },
      "golden_hash": "5787c492fb561d1bc43c7179eac44646e0174699e3b53a53ada31ef49a615922"
    }
  ]
}
